saliency_maps_metrics/__init__.py
saliency_maps_metrics/data_replace.py
saliency_maps_metrics/multi_step_metrics.py
saliency_maps_metrics/single_step_metrics.py
saliency_maps_metrics-0.0.26.dist-info/LICENSE
saliency_maps_metrics-0.0.26.dist-info/METADATA
saliency_maps_metrics-0.0.26.dist-info/WHEEL
saliency_maps_metrics-0.0.26.dist-info/top_level.txt
saliency_maps_metrics-0.0.26.dist-info/RECORD
