Metadata-Version: 2.1
Name: saliency_maps_metrics
Version: 0.0.26
Summary: This repository implements the faithfulness metrics mentionned in the paper --Computing and evaluating saliency maps for image classification: a tutorial-- in Pytorch.
Author-email: Tristan Gomez <tristan.gomez@univ-nantes.fr>
Project-URL: Homepage, https://github.com/TristanGomez44/metrics-saliency-maps
Project-URL: Bug Tracker, https://github.com/TristanGomez44/metrics-saliency-maps/issues
Classifier: Programming Language :: Python :: 3
Classifier: License :: OSI Approved :: MIT License
Classifier: Operating System :: OS Independent
Requires-Python: >=3.7
License-File: LICENSE
